dataclasses_xargs.py
dataclasses_xargs-1.0.2.dist-info/LICENSE
dataclasses_xargs-1.0.2.dist-info/METADATA
dataclasses_xargs-1.0.2.dist-info/WHEEL
dataclasses_xargs-1.0.2.dist-info/top_level.txt
dataclasses_xargs-1.0.2.dist-info/zip-safe
dataclasses_xargs-1.0.2.dist-info/RECORD
