Metadata-Version: 2.1
Name: dataclasses-xargs
Version: 1.0.2
Summary: An extension to the python dataclasses package that enables you to push the *args/*xargs
Home-page: https://github.com/scheibling/dataclasses-xargs.git
Author: Lars Scheibling
Author-email: it@scheibling.se
License: GPLv3
Keywords: python dataclass args xargs
Classifier: Programming Language :: Python :: 3
Classifier: License :: OSI Approved :: GNU General Public License v3 (GPLv3)
Classifier: Operating System :: OS Independent
Requires-Python: >=3.7
License-File: LICENSE
Requires-Dist: dataclasses >=0.6
